onedm/__init__.py
onedm/py.typed
onedm/sdf/__init__.py
onedm/sdf/common.py
onedm/sdf/data.py
onedm/sdf/definitions.py
onedm/sdf/document.py
onedm/sdf/exceptions.py
onedm/sdf/from_type.py
onedm/sdf/loader.py
onedm/sdf/registry.py
onedm/sdf/resolver.py
onedm/sdf/validate.py
onedm-0.3.1.dist-info/licenses/LICENSE
onedm-0.3.1.dist-info/METADATA
onedm-0.3.1.dist-info/WHEEL
onedm-0.3.1.dist-info/top_level.txt
onedm-0.3.1.dist-info/RECORD
