Metadata-Version: 2.4
Name: onedm
Version: 0.3.1
Summary: Common data model for IoT and IoT devices
Author-email: Christian Sandberg <christiansandberg@me.com>
Project-URL: Repository, https://github.com/christiansandberg/onedm.git
Project-URL: Issues, https://github.com/christiansandberg/onedm/issues
Keywords: iot,data model
Classifier: Development Status :: 3 - Alpha
Classifier: Intended Audience :: Developers
Classifier: Topic :: Software Development :: Libraries
Classifier: Topic :: File Formats
Classifier: License :: OSI Approved :: MIT License
Classifier: Programming Language :: Python :: 3
Requires-Python: >=3.10
License-File: LICENSE
Requires-Dist: pydantic>=2
Dynamic: license-file
